appium_flutter_utils/__init__.py
appium_flutter_utils/clicks.py
appium_flutter_utils/enter_text.py
appium_flutter_utils/finds_widget.py
appium_flutter_utils/scroll.py
appium_flutter_utils/setup.py
appium_flutter_utils/wait.py
appium_flutter_utils-0.1.0.dist-info/METADATA
appium_flutter_utils-0.1.0.dist-info/WHEEL
appium_flutter_utils-0.1.0.dist-info/licenses/LICENSE
appium_flutter_utils-0.1.0.dist-info/RECORD
