Metadata-Version: 2.1
Name: appium_flutter_utils
Version: 0.1.0
Summary: A package that provides lots of utils to make your Flutter Appium Testing easy.
Project-URL: Homepage, https://github.com/AradhyaNepal/AppiumFlutterUtils/tree/main/PythonUtils
Project-URL: Bug Tracker, https://github.com/AradhyaNepal/AppiumFlutterUtils/issues
Author-email: Aaradhya Gopal Nepal <aradhya.1441@gmail.com>
License-File: LICENSE
Classifier: License :: OSI Approved :: MIT License
Classifier: Operating System :: OS Independent
Classifier: Programming Language :: Python :: 3
Requires-Python: >=3.7
